external/org_openfst/pywrapfst.so
src/analyzer/bin/turkish.far
turkish_morphology/__init__.py
turkish_morphology/analysis_pb2.py
turkish_morphology/analyze.py
turkish_morphology/decompose.py
turkish_morphology/fst.py
turkish_morphology/generate.py
turkish_morphology/pretty_print.py
turkish_morphology/validate.py
turkish_morphology-1.2.5.dist-info/LICENSE
turkish_morphology-1.2.5.dist-info/METADATA
turkish_morphology-1.2.5.dist-info/WHEEL
turkish_morphology-1.2.5.dist-info/top_level.txt
turkish_morphology-1.2.5.dist-info/RECORD
