Metadata-Version: 2.1
Name: turkish-morphology
Version: 1.2.5
Summary: Turkish Morphology
Home-page: https://github.com/google-research/turkish-morphology
License: Apache 2.0
Download-URL: https://github.com/google-research/turkish-morphology/releases
Platform: UNKNOWN
Classifier: License :: OSI Approved :: Apache Software License
Classifier: Natural Language :: Turkish
Classifier: Operating System :: POSIX :: Linux
Classifier: Programming Language :: Python :: 3.9
Requires-Python: >=3.9
License-File: LICENSE
Requires-Dist: absl-py
Requires-Dist: protobuf
